do_yt/__init__.py
do_yt/yt_vdo.py
yt_video_downloader-0.0.1.dist-info/METADATA
yt_video_downloader-0.0.1.dist-info/WHEEL
yt_video_downloader-0.0.1.dist-info/entry_points.txt
yt_video_downloader-0.0.1.dist-info/top_level.txt
yt_video_downloader-0.0.1.dist-info/RECORD
